ultragrad/__init__.py
ultragrad/losses.py
ultragrad/nn.py
ultragrad/optim.py
ultragrad/py.typed
ultragrad/tensors.py
ultragrad-0.1.0.dist-info/METADATA
ultragrad-0.1.0.dist-info/WHEEL
ultragrad-0.1.0.dist-info/licenses/LICENSE
ultragrad-0.1.0.dist-info/RECORD
