Metadata-Version: 2.4
Name: ultragrad
Version: 0.1.0
Summary: An automatic gradient engine for training your all in one deep learning model
Author-email: Jaisurya <pjaisurya.ml@gmail.com>
License: MIT
License-File: LICENSE
Requires-Python: ==3.13.2
Requires-Dist: numpy>=2.3.1
Requires-Dist: pytest>=8.4.1
Requires-Dist: safetensors>=0.5.3
